numpydoc_decorator/__init__.py
numpydoc_decorator/example.py
numpydoc_decorator/impl.py
numpydoc_decorator-2.2.1.dist-info/LICENSE
numpydoc_decorator-2.2.1.dist-info/METADATA
numpydoc_decorator-2.2.1.dist-info/WHEEL
numpydoc_decorator-2.2.1.dist-info/RECORD
