Metadata-Version: 2.1
Name: numpydoc_decorator
Version: 2.2.1
Summary: 
Author: Alistair Miles
Author-email: alimanfoo@googlemail.com
Requires-Python: >=3.10,<3.13
Classifier: Programming Language :: Python :: 3
Classifier: Programming Language :: Python :: 3.10
Classifier: Programming Language :: Python :: 3.11
Classifier: Programming Language :: Python :: 3.12
Requires-Dist: typing_extensions
